pyneapple/__init__.py
pyneapple/pyneapple-0.1.0-SNAPSHOT-jar-with-dependencies.jar
pyneapple/regionalization/__init__.py
pyneapple/regionalization/expressive_maxp.py
pyneapple/regionalization/generalized_p.py
pyneapple/regionalization/maxp.py
pyneapple/regionalization/pruc.py
pyneapple/regionalization/scalable_maxp.py
pyneapple/regionalization/smpp_graph.py
pyneapple/tests/__init__.py
pyneapple/tests/testPruc.py
pyneapple/tests/tests_expressive_maxp.py
pyneapple/tests/tests_generalized_p.py
pyneapple/tests/tests_scalable_maxp.py
pyneapple/weight/__init__.py
pyneapple/weight/rook.py
pyneapple_lib-0.1.0.dist-info/METADATA
pyneapple_lib-0.1.0.dist-info/WHEEL
pyneapple_lib-0.1.0.dist-info/top_level.txt
pyneapple_lib-0.1.0.dist-info/RECORD
